{
    "Description": "HD 106252 b is a gas giant exoplanet that orbits a G-type star. Its mass is 6.93 Jupiters, it takes 4.2 years to complete one orbit of its star, and is 2.61 AU from its star. Its discovery was announced in 2002.",
    "Detection Method": "Radial Velocity",
    "Discovery Date": "2002",
    "Eccentricity": "0.48",
    "Id": "hd-106252-b",
    "Link": "https://exoplanets.nasa.gov//exoplanet-catalog/6728/hd-106252-b/",
    "Mass": "6.93 Jupiters",
    "Name": "hd-106252-b",
    "Orbital Period": "4.2 years",
    "Orbital Radius": "2.61 AU",
    "Planet Radius": "1.13 x Jupiter (estimate)",
    "Planet Type": "Gas Giant",
    "Uuid": "30b06e89-bbe6-4f7b-8257-d6e10aed8445",
    "images": {
        "0": {
            "Description": "Comparison with jupiter",
            "Path": "exoplanet_details/hd-106252-b/images/0.png"
        },
        "1": {
            "Description": "Comparison with earth",
            "Path": "exoplanet_details/hd-106252-b/images/1.png"
        },
        "2": {
            "Description": "Hd-106252-b",
            "Path": "exoplanet_details/hd-106252-b/images/2.png"
        },
        "Link": "https://eyes.nasa.gov/apps/exo/#/planet/HD_106252_b"
    }
}