{
    "Description": "K2-329 b is a gas giant exoplanet that orbits a K-type star. Its mass is 0.26 Jupiters, it takes 12.5 days to complete one orbit of its star, and is 0.1016 AU from its star. Its discovery was announced in 2020.",
    "Detection Method": "Transit",
    "Discovery Date": "2020",
    "Eccentricity": "0.07",
    "Id": "k2-329-b",
    "Link": "https://exoplanets.nasa.gov//exoplanet-catalog/7810/k2-329-b/",
    "Mass": "0.26 Jupiters",
    "Name": "k2-329-b",
    "Orbital Period": "12.5 days",
    "Orbital Radius": "0.1016 AU",
    "Planet Radius": "0.774 x Jupiter",
    "Planet Type": "Gas Giant",
    "Uuid": "512c9fc6-ee1d-4d0f-b9b6-6e3f81672e70",
    "images": {
        "0": {
            "Description": "Comparison with jupiter",
            "Path": "exoplanet_details/k2-329-b/images/0.png"
        },
        "1": {
            "Description": "Comparison with earth",
            "Path": "exoplanet_details/k2-329-b/images/1.png"
        },
        "2": {
            "Description": "K2-329-b",
            "Path": "exoplanet_details/k2-329-b/images/2.png"
        },
        "Link": "https://eyes.nasa.gov/apps/exo/#/planet/K2-329_b"
    }
}